pybeyeonics/__init__.py
pybeyeonics-0.0.1.dist-info/LICENSE.txt
pybeyeonics-0.0.1.dist-info/METADATA
pybeyeonics-0.0.1.dist-info/WHEEL
pybeyeonics-0.0.1.dist-info/top_level.txt
pybeyeonics-0.0.1.dist-info/RECORD
