Metadata-Version: 2.1
Name: pybeyeonics
Version: 0.0.1
Summary: A Python package
Author: bey
Author-email: no@name.com
Classifier: Programming Language :: Python :: 3
Classifier: License :: OSI Approved :: MIT License
Classifier: Operating System :: OS Independent
Requires-Python: >=3.6
License-File: LICENSE.txt
